snqs_kpm/__init__.py
snqs_kpm/config.py
snqs_kpm/chem/__init__.py
snqs_kpm/chem/_psi4_conversion_functions.py
snqs_kpm/chem/_pyscf_molecular_data.py
snqs_kpm/chem/_run_psi4.py
snqs_kpm/chem/_run_pyscf.py
snqs_kpm/chem/basis_data.py
snqs_kpm/chem/get_H2_chains.py
snqs_kpm/chem/get_active_space.py
snqs_kpm/chem/get_dipole_operator.py
snqs_kpm/chem/get_mean_field.py
snqs_kpm/chem/get_molecular_data.py
snqs_kpm/chem/get_n_qubits_k_terms.py
snqs_kpm/chem/get_one_particle.py
snqs_kpm/chem/get_two_particle.py
snqs_kpm/chem/pubchem.py
snqs_kpm/chem/utils_geometry.py
snqs_kpm/kpm/__init__.py
snqs_kpm/kpm/chebyshev_method.py
snqs_kpm/kpm/cpapy.py
snqs_kpm/kpm/kpmpy.py
snqs_kpm/kpm/utils_kpm.py
snqs_kpm/linalg/__init__.py
snqs_kpm/linalg/givens_rotations.py
snqs_kpm/nqs/__init__.py
snqs_kpm/nqs/_base.py
snqs_kpm/nqs/_base_moments.py
snqs_kpm/nqs/run.py
snqs_kpm/nqs/run_moments.py
snqs_kpm/nqs/network/__init__.py
snqs_kpm/nqs/network/wavefunction.py
snqs_kpm/nqs/network/network/__init__.py
snqs_kpm/nqs/network/network/activations.py
snqs_kpm/nqs/network/network/base.py
snqs_kpm/nqs/network/network/nade.py
snqs_kpm/nqs/network/network/torch_utils.py
snqs_kpm/nqs/optimizer/__init__.py
snqs_kpm/nqs/optimizer/dipole.py
snqs_kpm/nqs/optimizer/energy.py
snqs_kpm/nqs/optimizer/hamiltonian.py
snqs_kpm/nqs/optimizer/utils.py
snqs_kpm/nqs/utils/__init__.py
snqs_kpm/nqs/utils/ascii.py
snqs_kpm/nqs/utils/complex.py
snqs_kpm/nqs/utils/functional.py
snqs_kpm/nqs/utils/get_Omega.py
snqs_kpm/nqs/utils/hilbert.py
snqs_kpm/nqs/utils/optim.py
snqs_kpm/nqs/utils/plotting.py
snqs_kpm/nqs/utils/system.py
snqs_kpm/ops/__init__.py
snqs_kpm/ops/_abstract_observable.py
snqs_kpm/ops/_abstract_operator.py
snqs_kpm/ops/_discrete_operator.py
snqs_kpm/ops/_discrete_operator_jax.py
snqs_kpm/ops/_lazy.py
snqs_kpm/ops/base.py
snqs_kpm/ops/boson_operator.py
snqs_kpm/ops/diagonal_coulomb_hamiltonian.py
snqs_kpm/ops/doci_hamiltonian.py
snqs_kpm/ops/fermion_operator.py
snqs_kpm/ops/interaction_operator.py
snqs_kpm-0.1.9.dist-info/METADATA
snqs_kpm-0.1.9.dist-info/WHEEL
snqs_kpm-0.1.9.dist-info/top_level.txt
snqs_kpm-0.1.9.dist-info/RECORD
