Metadata-Version: 2.1
Name: snqs-kpm
Version: 0.1.9
Summary: Scalable Neural Quantum State based Kernel Polynomial Method for Optical Properties from the First Principle
Home-page: https://github.com/Weitheskmt/sNQS-KPM
Author: Wei Liu
Author-email: liuwei.chem.phys@gmail.com
License: MIT
Classifier: Programming Language :: Python :: 3
Classifier: License :: OSI Approved :: MIT License
Classifier: Operating System :: OS Independent
Requires-Python: >=3.11
